{
  "parent": "unusual_prehistory:jurassic_root",
  "criteria": {
    "revive_brachiosaurus": {
      "conditions": {
        "entity": [
          {
            "condition": "minecraft:entity_properties",
            "entity": "this",
            "predicate": {
              "type": "unusual_prehistory:brachiosaurus"
            }
          }
        ]
      },
      "trigger": "minecraft:summoned_entity"
    }
  },
  "display": {
    "description": {
      "translate": "advancements.unusual_prehistory.revive_brachiosaurus.description"
    },
    "hidden": true,
    "icon": {
      "count": 1,
      "id": "unusual_prehistory:brachiosaurus_egg"
    },
    "title": {
      "translate": "advancements.unusual_prehistory.revive_brachiosaurus.title"
    }
  },
  "requirements": [
    [
      "revive_brachiosaurus"
    ]
  ],
  "rewards": {
    "experience": 5
  },
  "sends_telemetry_event": true
}