{
  "type": "minecraft:archaeology",
  "pools": [
    {
      "bonus_rolls": 0.0,
      "entries": [
        {
          "type": "minecraft:item",
          "name": "unusual_prehistory:fury_fossil",
          "weight": 1
        },
        {
          "type": "minecraft:item",
          "name": "unusual_prehistory:prickly_fossil",
          "weight": 1
        },
        {
          "type": "minecraft:item",
          "name": "unusual_prehistory:rugose_fossil",
          "weight": 1
        },
        {
          "type": "minecraft:item",
          "name": "unusual_prehistory:boar_tooth_fossil",
          "weight": 1
        },
        {
          "type": "minecraft:item",
          "name": "unusual_prehistory:meltdown_fossil",
          "weight": 1
        }
      ],
      "rolls": 1.0
    }
  ],
  "random_sequence": "unusual_prehistory:archaeology/fossils/mesozoic_rare"
}