{
  "type": "minecraft:archaeology",
  "pools": [
    {
      "bonus_rolls": 0.0,
      "entries": [
        {
          "type": "minecraft:item",
          "name": "unusual_prehistory:thermal_fossil",
          "weight": 3
        },
        {
          "type": "minecraft:item",
          "name": "unusual_prehistory:plumage_fossil",
          "weight": 4
        },
        {
          "type": "minecraft:item",
          "name": "unusual_prehistory:tarifying_disc",
          "weight": 1
        }
      ],
      "rolls": 1.0
    }
  ],
  "random_sequence": "unusual_prehistory:archaeology/tar_pit_epic"
}